Metadata-Version: 2.4
Name: sgwt
Version: 0.3.7
Summary: Sparse Tools for the Spectral Graph Wavelet Transformation and Graph Convolution
Author-email: Luke Lowery <lukel@tamu.edu>
Project-URL: Homepage, https://github.com/lukelowry/sgwt
Project-URL: Repository, https://github.com/lukelowry/sgwt
Project-URL: Bug Tracker, https://github.com/lukelowry/sgwt/issues
Classifier: Programming Language :: Python :: 3
Classifier: License :: OSI Approved :: GNU General Public License v3 (GPLv3)
Classifier: Intended Audience :: Science/Research
Classifier: Topic :: Scientific/Engineering
Requires-Python: >=3.7
License-File: LICENSE
Requires-Dist: numpy
Requires-Dist: scipy
Requires-Dist: importlib-resources>=5.0; python_version < "3.9"
Provides-Extra: dev
Requires-Dist: matplotlib; extra == "dev"
Provides-Extra: test
Requires-Dist: pytest; extra == "test"
Requires-Dist: pytest-cov; extra == "test"
Requires-Dist: pytest-benchmark; extra == "test"
Provides-Extra: docs
Requires-Dist: sphinx; extra == "docs"
Requires-Dist: numpydoc; extra == "docs"
Requires-Dist: sphinxcontrib-bibtex; extra == "docs"
Requires-Dist: sphinx-gallery; extra == "docs"
Requires-Dist: memory_profiler; extra == "docs"
Requires-Dist: sphinx-rtd-theme; extra == "docs"
Requires-Dist: sphinx-copybutton; extra == "docs"
Dynamic: license-file
